Workbook

Sheet Dashboard
A1: Landlord Portfolio Dashboard - 10 Properties
A3: Metric | B3: Value | D3: PropertyID | E3: Monthly Rent | F3: Status
A4: Total Properties | B4: =COUNTA(Properties!A2:A11) -> 10 | D4: =Properties!A2 -> P001 | E4: =Properties!I2 -> 1500 | F4: =Properties!H2 -> Occupied
B5: =COUNTIF(Properties!H2:H11,"Occupied") -> 8 | D5: =Properties!A3 -> P002 | E5: =Properties!I3 -> 2100 | F5: =Properties!H3 -> Occupied
A6: Available Properties | B6: =COUNTIF(Properties!H2:H11,"Available") -> 2 | D6: =Properties!A4 -> P003 | E6: =Properties!I4 -> 1200 | F6: =Properties!H4 -> Occupied
A7: Monthly Rent Roll | B7: =SUM(Properties!I2:I11) -> 18900 | D7: =Properties!A5 -> P004 | E7: =Properties!I5 -> 2500 | F7: =Properties!H5 -> Occupied
A8: Annual Rent Roll | B8: =SUM(Properties!K2:K11) -> 226800 | D8: =Properties!A6 -> P005 | E8: =Properties!I6 -> 1600 | F8: =Properties!H6 -> Occupied
A9: Current Arrears | B9: =SUM('Rent Payments'!I2:I200) -> 3100 | D9: =Properties!A7 -> P006 | E9: =Properties!I7 -> 2000 | F9: =Properties!H7 -> Occupied
A10: Open Maintenance | B10: =COUNTIF(Maintenance!G2:G100,"Open") -> 1 | D10: =Properties!A8 -> P007 | E10: =Properties!I8 -> 1100 | F10: =Properties!H8 -> Occupied
D11: =Properties!A9 -> P008 | E11: =Properties!I9 -> 3000 | F11: =Properties!H9 -> Occupied
D12: =Properties!A10 -> P009 | E12: =Properties!I10 -> 1700 | F12: =Properties!H10 -> Available
D13: =Properties!A11 -> P010 | E13: =Properties!I11 -> 2200 | F13: =Properties!H11 -> Available

Sheet Landlords
A1: LandlordID | B1: Name | C1: Phone | D1: Email | E1: Address | F1: Notes
A2: L001 | B2: Main Landlord | C2: 07123 456789 | D2: landlord@email.com | E2: Reading / UK | F2: Portfolio of 10 properties

Sheet Properties
A1: PropertyID | B1: LandlordID | C1: Address | D1: Town/City | E1: Postcode | F1: Type | G1: Bedrooms | H1: Status | I1: Monthly Rent | J1: MortgageID | K1: Annual Rent | L1: Notes
A2: P001 | B2: L001 | C2: 1 High Street | D2: Reading | E2: RG1 1AA | F2: Flat | G2: 2 | H2: Occupied | I2: 1500 | J2: M001 | K2: =I2*12 -> 18000
A3: P002 | B3: L001 | C3: 2 High Street | D3: Reading | E3: RG2 1AA | F3: House | G3: 3 | H3: Occupied | I3: 2100 | J3: M002 | K3: =I3*12 -> 25200
A4: P003 | B4: L001 | C4: 3 High Street | D4: Reading | E4: RG3 1AA | F4: Flat | G4: 1 | H4: Occupied | I4: 1200 | J4: M003 | K4: =I4*12 -> 14400
A5: P004 | B5: L001 | C5: 4 High Street | D5: Reading | E5: RG4 1AA | F5: House | G5: 4 | H5: Occupied | I5: 2500 | J5: M004 | K5: =I5*12 -> 30000
A6: P005 | B6: L001 | C6: 5 High Street | D6: Reading | E6: RG5 1AA | F6: Flat | G6: 2 | H6: Occupied | I6: 1600 | J6: M005 | K6: =I6*12 -> 19200
A7: P006 | B7: L001 | C7: 6 High Street | D7: Reading | E7: RG6 1AA | F7: House | G7: 3 | H7: Occupied | I7: 2000 | J7: M006 | K7: =I7*12 -> 24000
A8: P007 | B8: L001 | C8: 7 High Street | D8: Reading | E8: RG7 1AA | F8: Flat | G8: 1 | H8: Occupied | I8: 1100 | J8: M007 | K8: =I8*12 -> 13200
A9: P008 | B9: L001 | C9: 8 High Street | D9: Reading | E9: RG8 1AA | F9: House | G9: 5 | H9: Occupied | I9: 3000 | J9: M008 | K9: =I9*12 -> 36000
A10: P009 | B10: L001 | C10: 9 High Street | D10: Reading | E10: RG9 1AA | F10: Flat | G10: 2 | H10: Available | I10: 1700 | J10: M009 | K10: =I10*12 -> 20400
A11: P010 | B11: L001 | C11: 10 High Street | D11: Reading | E11: RG10 1AA | F11: House | G11: 3 | H11: Available | I11: 2200 | J11: M010 | K11: =I11*12 -> 26400

Sheet Tenants
A1: TenantID | B1: Name | C1: Phone | D1: Email | E1: Emergency Contact | F1: Notes
A2: T001 | B2: Sarah Jones | C2: 07111 111111 | D2: sarah.jones@email.com
A3: T002 | B3: David Brown | C3: 07222 222222 | D3: david.brown@email.com
A4: T003 | B4: Aisha Khan | C4: 07333 333333 | D4: aisha.khan@email.com
A5: T004 | B5: Michael Lee | C5: 07444 444444 | D5: michael.lee@email.com
A6: T005 | B6: Priya Patel | C6: 07555 555555 | D6: priya.patel@email.com
A7: T006 | B7: James Wilson | C7: 07666 666666 | D7: james.wilson@email.com
A8: T007 | B8: Emma Taylor | C8: 07777 777777 | D8: emma.taylor@email.com
A9: T008 | B9: Mohammed Ali | C9: 07888 888888 | D9: mohammed.ali@email.com
A10: T009 | B10: Vacant
A11: T010 | B11: Vacant

Sheet Tenancies
A1: TenancyID | B1: PropertyID | C1: TenantID | D1: Start Date | E1: End Date | F1: Monthly Rent | G1: Deposit | H1: Deposit Protected? | I1: Status | J1: Days to End | K1: Notes
A2: TN001 | B2: P001 | C2: T001 | D2: 46023 | E2: 46387 | F2: =_xludf.XLOOKUP(B2,Properties!A:A,Properties!I:I,0) -> #NAME? | G2: =F2 -> #NAME? | H2: Yes | I2: Active | J2: =IF(I2="Active",E2-TODAY(),"") -> 214
A3: TN002 | B3: P002 | C3: T002 | D3: 46054 | E3: 46053 | F3: =_xludf.XLOOKUP(B3,Properties!A:A,Properties!I:I,0) -> #NAME? | G3: =F3 -> #NAME? | H3: Yes | I3: Active | J3: =IF(I3="Active",E3-TODAY(),"") -> -120
A4: TN003 | B4: P003 | C4: T003 | D4: 46023 | E4: 46387 | F4: =_xludf.XLOOKUP(B4,Properties!A:A,Properties!I:I,0) -> #NAME? | G4: =F4 -> #NAME? | H4: Yes | I4: Active | J4: =IF(I4="Active",E4-TODAY(),"") -> 214
A5: TN004 | B5: P004 | C5: T004 | D5: 46054 | E5: 46053 | F5: =_xludf.XLOOKUP(B5,Properties!A:A,Properties!I:I,0) -> #NAME? | G5: =F5 -> #NAME? | H5: Yes | I5: Active | J5: =IF(I5="Active",E5-TODAY(),"") -> -120
A6: TN005 | B6: P005 | C6: T005 | D6: 46023 | E6: 46387 | F6: =_xludf.XLOOKUP(B6,Properties!A:A,Properties!I:I,0) -> #NAME? | G6: =F6 -> #NAME? | H6: Yes | I6: Active | J6: =IF(I6="Active",E6-TODAY(),"") -> 214
A7: TN006 | B7: P006 | C7: T006 | D7: 46054 | E7: 46053 | F7: =_xludf.XLOOKUP(B7,Properties!A:A,Properties!I:I,0) -> #NAME? | G7: =F7 -> #NAME? | H7: Yes | I7: Active | J7: =IF(I7="Active",E7-TODAY(),"") -> -120
A8: TN007 | B8: P007 | C8: T007 | D8: 46023 | E8: 46387 | F8: =_xludf.XLOOKUP(B8,Properties!A:A,Properties!I:I,0) -> #NAME? | G8: =F8 -> #NAME? | H8: Yes | I8: Active | J8: =IF(I8="Active",E8-TODAY(),"") -> 214
A9: TN008 | B9: P008 | C9: T008 | D9: 46054 | E9: 46053 | F9: =_xludf.XLOOKUP(B9,Properties!A:A,Properties!I:I,0) -> #NAME? | G9: =F9 -> #NAME? | H9: Yes | I9: Active | J9: =IF(I9="Active",E9-TODAY(),"") -> -120

Sheet Rent Payments
A1: PaymentID | B1: PropertyID | C1: TenantID | D1: Due Date | E1: Paid Date | F1: Amount Due | G1: Amount Paid | H1: Status | I1: Arrears | J1: Month | K1: Notes
A2: R0001 | B2: P001 | C2: T001 | D2: 46023 | E2: 46023 | F2: 1500 | G2: 1500 | H2: Paid | I2: =F2-G2 -> 0 | J2: =TEXT(D2,"mmm yyyy") -> Jan 2026
A3: R0002 | B3: P002 | C3: T002 | D3: 46023 | E3: 46023 | F3: 2100 | G3: 2100 | H3: Paid | I3: =F3-G3 -> 0 | J3: =TEXT(D3,"mmm yyyy") -> Jan 2026
A4: R0003 | B4: P003 | C4: T003 | D4: 46023 | E4: 46023 | F4: 1200 | G4: 1200 | H4: Paid | I4: =F4-G4 -> 0 | J4: =TEXT(D4,"mmm yyyy") -> Jan 2026
A5: R0004 | B5: P004 | C5: T004 | D5: 46023 | E5: 46023 | F5: 2500 | G5: 2500 | H5: Paid | I5: =F5-G5 -> 0 | J5: =TEXT(D5,"mmm yyyy") -> Jan 2026
A6: R0005 | B6: P005 | C6: T005 | D6: 46023 | E6: 46023 | F6: 1600 | G6: 1600 | H6: Paid | I6: =F6-G6 -> 0 | J6: =TEXT(D6,"mmm yyyy") -> Jan 2026
A7: R0006 | B7: P006 | C7: T006 | D7: 46023 | E7: 46023 | F7: 2000 | G7: 2000 | H7: Paid | I7: =F7-G7 -> 0 | J7: =TEXT(D7,"mmm yyyy") -> Jan 2026
A8: R0007 | B8: P007 | C8: T007 | D8: 46023 | E8: 46023 | F8: 1100 | G8: 1100 | H8: Paid | I8: =F8-G8 -> 0 | J8: =TEXT(D8,"mmm yyyy") -> Jan 2026
A9: R0008 | B9: P008 | C9: T008 | D9: 46023 | E9: 46023 | F9: 3000 | G9: 3000 | H9: Paid | I9: =F9-G9 -> 0 | J9: =TEXT(D9,"mmm yyyy") -> Jan 2026
A10: R0009 | B10: P001 | C10: T001 | D10: 46054 | E10: 46054 | F10: 1500 | G10: 1500 | H10: Paid | I10: =F10-G10 -> 0 | J10: =TEXT(D10,"mmm yyyy") -> Feb 2026
A11: R0010 | B11: P002 | C11: T002 | D11: 46054 | E11: 46054 | F11: 2100 | G11: 2100 | H11: Paid | I11: =F11-G11 -> 0 | J11: =TEXT(D11,"mmm yyyy") -> Feb 2026
A12: R0011 | B12: P003 | C12: T003 | D12: 46054 | E12: 46054 | F12: 1200 | G12: 1200 | H12: Paid | I12: =F12-G12 -> 0 | J12: =TEXT(D12,"mmm yyyy") -> Feb 2026
A13: R0012 | B13: P004 | C13: T004 | D13: 46054 | E13: 46054 | F13: 2500 | G13: 2500 | H13: Paid | I13: =F13-G13 -> 0 | J13: =TEXT(D13,"mmm yyyy") -> Feb 2026
... A38: R0037 | B38: P005 | C38: T005 | D38: 46143 | E38: 46143 | F38: 1600 | G38: 1600 | H38: Paid | I38: =F38-G38 -> 0 | J38: =TEXT(D38,"mmm yyyy") -> May 2026
A39: R0038 | B39: P006 | C39: T006 | D39: 46143 | F39: 2000 | G39: 0 | H39: Late | I39: =F39-G39 -> 2000 | J39: =TEXT(D39,"mmm yyyy") -> May 2026
A40: R0039 | B40: P007 | C40: T007 | D40: 46143 | E40: 46143 | F40: 1100 | G40: 1100 | H40: Paid | I40: =F40-G40 -> 0 | J40: =TEXT(D40,"mmm yyyy") -> May 2026
A41: R0040 | B41: P008 | C41: T008 | D41: 46143 | E41: 46143 | F41: 3000 | G41: 3000 | H41: Paid | I41: =F41-G41 -> 0 | J41: =TEXT(D41,"mmm yyyy") -> May 2026
A42: R0041 | B42: P001 | C42: T001 | D42: 46174 | E42: 46174 | F42: 1500 | G42: 1500 | H42: Paid | I42: =F42-G42 -> 0 | J42: =TEXT(D42,"mmm yyyy") -> Jun 2026
A43: R0042 | B43: P002 | C43: T002 | D43: 46174 | E43: 46174 | F43: 2100 | G43: 2100 | H43: Paid | I43: =F43-G43 -> 0 | J43: =TEXT(D43,"mmm yyyy") -> Jun 2026
A44: R0043 | B44: P003 | C44: T003 | D44: 46174 | E44: 46174 | F44: 1200 | G44: 1200 | H44: Paid | I44: =F44-G44 -> 0 | J44: =TEXT(D44,"mmm yyyy") -> Jun 2026
A45: R0044 | B45: P004 | C45: T004 | D45: 46174 | E45: 46174 | F45: 2500 | G45: 2500 | H45: Paid | I45: =F45-G45 -> 0 | J45: =TEXT(D45,"mmm yyyy") -> Jun 2026
A46: R0045 | B46: P005 | C46: T005 | D46: 46174 | E46: 46174 | F46: 1600 | G46: 1600 | H46: Paid | I46: =F46-G46 -> 0 | J46: =TEXT(D46,"mmm yyyy") -> Jun 2026
A47: R0046 | B47: P006 | C47: T006 | D47: 46174 | E47: 46174 | F47: 2000 | G47: 2000 | H47: Paid | I47: =F47-G47 -> 0 | J47: =TEXT(D47,"mmm yyyy") -> Jun 2026
A48: R0047 | B48: P007 | C48: T007 | D48: 46174 | E48: 46174 | F48: 1100 | G48: 1100 | H48: Paid | I48: =F48-G48 -> 0 | J48: =TEXT(D48,"mmm yyyy") -> Jun 2026
A49: R0048 | B49: P008 | C49: T008 | D49: 46174 | E49: 46174 | F49: 3000 | G49: 3000 | H49: Paid | I49: =F49-G49 -> 0 | J49: =TEXT(D49,"mmm yyyy") -> Jun 2026

Sheet Maintenance
A1: MaintenanceID | B1: PropertyID | C1: Reported Date | D1: Description | E1: ContractorID | F1: Priority | G1: Status | H1: Cost Estimate | I1: Actual Cost | J1: Completed Date | K1: Notes
A2: M001 | B2: P001 | C2: 46032 | D2: Boiler service | E2: C001 | F2: Medium | G2: Completed | H2: 120 | I2: 120 | J2: 46034
A3: M002 | B3: P002 | C3: 46068 | D3: Plumbing repair | E3: C002 | F3: High | G3: Completed | H3: 250 | I3: 240 | J3: 46069
A4: M003 | B4: P006 | C4: 46162 | D4: Roof leak check | E4: C003 | F4: High | G4: Open | H4: 500
A5: M004 | B5: P008 | C5: 46167 | D5: Garden fence repair | E5: C004 | F5: Low | G5: In Progress | H5: 300

Sheet Certificates
A1: CertificateID | B1: PropertyID | C1: Certificate Type | D1: Issue Date | E1: Expiry Date | F1: Status | G1: Provider | H1: Cost | I1: Document Link | J1: Notes
A2: CF0001 | B2: P001 | C2: EPC | D2: 46023 | E2: 47849 | F2: Valid | H2: 0
A3: CF0002 | B3: P001 | C3: Gas Safety | D3: 46023 | E3: 46388 | F3: Valid | H3: 0
A4: CF0003 | B4: P001 | C4: EICR | D4: 46023 | E4: 47849 | F4: Valid | H4: 0
A5: CF0004 | B5: P002 | C5: EPC | D5: 46023 | E5: 47849 | F5: Valid | H5: 0
A6: CF0005 | B6: P002 | C6: Gas Safety | D6: 46023 | E6: 46388 | F6: Valid | H6: 0
A7: CF0006 | B7: P002 | C7: EICR | D7: 46023 | E7: 47849 | F7: Valid | H7: 0
A8: CF0007 | B8: P003 | C8: EPC | D8: 46023 | E8: 47849 | F8: Valid | H8: 0
A9: CF0008 | B9: P003 | C9: Gas Safety | D9: 46023 | E9: 46388 | F9: Valid | H9: 0
A10: CF0009 | B10: P003 | C10: EICR | D10: 46023 | E10: 47849 | F10: Valid | H10: 0
A11: CF0010 | B11: P004 | C11: EPC | D11: 46023 | E11: 47849 | F11: Valid | H11: 0
A12: CF0011 | B12: P004 | C12: Gas Safety | D12: 46023 | E12: 46388 | F12: Valid | H12: 0
A13: CF0012 | B13: P004 | C13: EICR | D13: 46023 | E13: 47849 | F13: Valid | H13: 0
... A31: CF0030 | B31: P010 | C31: EICR | D31: 46023 | E31: 47849 | F31: Valid | H31: 0

Sheet Mortgages
A1: MortgageID | B1: PropertyID | C1: Lender | D1: Balance | E1: Monthly Payment | F1: Interest Rate | G1: Fixed Until | H1: Notes
A2: M001 | B2: P001 | C2: Bank / Lender | D2: 160000 | E2: 730 | F2: 0.052 | G2: 47118
A3: M002 | B3: P002 | C3: Bank / Lender | D3: 170000 | E3: 760 | F3: 0.052 | G3: 47118
A4: M003 | B4: P003 | C4: Bank / Lender | D4: 180000 | E4: 790 | F4: 0.052 | G4: 47118
A5: M004 | B5: P004 | C5: Bank / Lender | D5: 190000 | E5: 820 | F5: 0.052 | G5: 47118
A6: M005 | B6: P005 | C6: Bank / Lender | D6: 200000 | E6: 850 | F6: 0.052 | G6: 47118
A7: M006 | B7: P006 | C7: Bank / Lender | D7: 210000 | E7: 880 | F7: 0.052 | G7: 47118
A8: M007 | B8: P007 | C8: Bank / Lender | D8: 220000 | E8: 910 | F8: 0.052 | G8: 47118
A9: M008 | B9: P008 | C9: Bank / Lender | D9: 230000 | E9: 940 | F9: 0.052 | G9: 47118
A10: M009 | B10: P009 | C10: Bank / Lender | D10: 240000 | E10: 970 | F10: 0.052 | G10: 47118
A11: M010 | B11: P010 | C11: Bank / Lender | D11: 250000 | E11: 1000 | F11: 0.052 | G11: 47118

Sheet Contractors
A1: ContractorID | B1: Company/Name | C1: Trade | D1: Phone | E1: Email | F1: Area | G1: Insurance Checked? | H1: Notes
A2: C001 | B2: ABC Gas Services | C2: Gas engineer | F2: Reading | G2: Yes
A3: C002 | B3: Rapid Plumbing | C3: Plumber | F3: Reading | G3: Yes
A4: C003 | B4: RoofCare | C4: Roofer | F4: Reading | G4: No
A5: C004 | B5: GardenFix | C5: Gardener/Fencing | F5: Reading | G5: No

Sheet Lists
A1: Property Type | B1: Status | C1: Tenancy Status | D1: Payment Status | E1: Maintenance Status | F1: Certificate Type | G1: Certificate Status
A2: Flat | B2: Available | C2: Active | D2: Paid | E2: Open | F2: EPC | G2: Valid
A3: House | B3: Occupied | C3: Ending Soon | D3: Due | E3: In Progress | F3: Gas Safety | G3: Expiring Soon
A4: HMO | B4: Maintenance | C4: Ended | D4: Late | E4: Completed | F4: EICR | G4: Expired
A5: Studio | B5: Notice Given | C5: Prospect | D5: Partial | E5: Deferred | F5: Landlord Insurance | G5: Not Required
A6: Commercial | B6: Under Offer | F6: HMO Licence
F7: Smoke Alarm Check
